odoo/addons/sale_order_recurrence/README.rst
odoo/addons/sale_order_recurrence/__init__.py
odoo/addons/sale_order_recurrence/__manifest__.py
odoo/addons/sale_order_recurrence/i18n/fr.po
odoo/addons/sale_order_recurrence/i18n/sale_order_recurrence.pot
odoo/addons/sale_order_recurrence/models/__init__.py
odoo/addons/sale_order_recurrence/models/sale_order_recurrence_wizard.py
odoo/addons/sale_order_recurrence/models/sale_order_recurrence_wizard_date_line.py
odoo/addons/sale_order_recurrence/readme/CONTRIBUTORS.rst
odoo/addons/sale_order_recurrence/readme/DESCRIPTION.rst
odoo/addons/sale_order_recurrence/readme/USAGE.rst
odoo/addons/sale_order_recurrence/security/ir.model.access.csv
odoo/addons/sale_order_recurrence/static/description/icon.png
odoo/addons/sale_order_recurrence/static/description/index.html
odoo/addons/sale_order_recurrence/static/description/quotations_created_with_wizard.png
odoo/addons/sale_order_recurrence/static/description/sale_order_duplication_wizard_form.png
odoo/addons/sale_order_recurrence/tests/__init__.py
odoo/addons/sale_order_recurrence/tests/test_sale_order_recurrence.py
odoo/addons/sale_order_recurrence/views/action.xml
odoo/addons/sale_order_recurrence/views/view_sale_order_recurrence_wizard.xml
odoo_addon_sale_order_recurrence-16.0.1.0.0.2.dist-info/METADATA
odoo_addon_sale_order_recurrence-16.0.1.0.0.2.dist-info/WHEEL
odoo_addon_sale_order_recurrence-16.0.1.0.0.2.dist-info/top_level.txt
odoo_addon_sale_order_recurrence-16.0.1.0.0.2.dist-info/RECORD
